nostpy_gui/__init__.py
nostpy_gui/delete.py
nostpy_gui/event.py
nostpy_gui/landing.py
nostpy_gui/main.py
nostpy_gui/manage.py
nostpy_gui/query.py
nostpy_gui-0.1.12.dist-info/LICENSE
nostpy_gui-0.1.12.dist-info/METADATA
nostpy_gui-0.1.12.dist-info/WHEEL
nostpy_gui-0.1.12.dist-info/entry_points.txt
nostpy_gui-0.1.12.dist-info/top_level.txt
nostpy_gui-0.1.12.dist-info/RECORD
