Metadata-Version: 2.1
Name: nostpy-gui
Version: 0.1.12
Summary: A nostr relay management client
Author-email: Brian Hartford <bh419@protonmail.com>
License: MIT License
Project-URL: repository, https://github.com/UTXOnly/nostpy-gui
Requires-Python: >=3.7
License-File: LICENSE
Requires-Dist: asyncio
Requires-Dist: secp256k1
Requires-Dist: websockets
